{
  "console_variants": [
    {
      "name": "PS5 Pro",
      "price": 550.0,
      "exclude_words": ["PlayStation", "PS5"] ,
      "search_bases": ["https://store.playstation.com/", "https://www.amazon.com/s?field-keywords=PS5+Pro"]
    },
    {
      "name": "Xbox Series X Galaxy Black",
      "price": 320.0,
      "exclude_words": ["Xbox Series X", "Xbox One"] ,
      "search_bases": ["https://www.xbox.com/", "https://www.amazon.com/s?field-keywords=Xbox+Series+X+Galaxy+Black"]
    },
    {
      "name": "Xbox Series S Galaxy Black",
      "price": 170.0,
      "exclude_words": ["Xbox Series S", "Xbox One"] ,
      "search_bases": ["https://www.xbox.com/", "https://www.amazon.com/s?field-keywords=Xbox+Series+S+Galaxy+Black"]
    },
    {
      "name": "Steam Deck OLED 512GB",
      "price": 420.0,
      "exclude_words": ["Steam Deck"] ,
      "search_bases": ["https://store.steampowered.com/", "https://www.amazon.com/s?field-keywords=Steam+Deck+OLED+512GB"]
    },
    {
      "name": "Steam Deck OLED 1TB",
      "price": 480.0,
      "exclude_words": ["Steam Deck"] ,
      "search_bases": ["https://store.steampowered.com/", "https://www.amazon.com/s?field-keywords=Steam+Deck+OLED+1TB"]
    },
    {
      "name": "ROG Ally Z1 Extreme 512GB",
      "price": 320.0,
      "exclude_words": ["ROG Ally"] ,
      "search_bases": ["https://rog.gg/ally", "https://www.amazon.com/s?field-keywords=ROG+Ally+Z1+Extreme+512GB"]
    },
    {
      "name": "ROG Ally X 1TB",
      "price": 450.0,
      "exclude_words": ["ROG Ally"] ,
      "search_bases": ["https://rog.gg/ally", "https://www.amazon.com/s?field-keywords=ROG+Ally+X+1TB"]
    }
  ]
}